DrawLevels/__init__.py
DrawLevels-0.2.12.dist-info/LICENSE
DrawLevels-0.2.12.dist-info/METADATA
DrawLevels-0.2.12.dist-info/WHEEL
DrawLevels-0.2.12.dist-info/top_level.txt
DrawLevels-0.2.12.dist-info/RECORD
