Metadata-Version: 2.1
Name: DrawLevels
Version: 0.2.12
Summary: A package for quickly generating simple nuclear level schemes.
Home-page: https://github.com/TheThirdFool/DrawLevels
Author: TheThirdFool
Author-email: danielfh.dfh@gmail.com
License: UNKNOWN
Keywords: Nuclear Physics Level Scheme
Platform: UNKNOWN
Classifier: Programming Language :: Python :: 3
Classifier: Programming Language :: Python :: 3.6
Classifier: Programming Language :: Python :: 3.7
Classifier: Programming Language :: Python :: 3.8
Classifier: License :: OSI Approved :: MIT License
Classifier: Operating System :: OS Independent
Requires-Dist: pycairo
